whaller_client/__init__.py
whaller_client/api.py
whaller_client/auth.py
whaller_client/client.py
whaller_client/exceptions.py
whaller_client/logger.py
whaller_client-0.1.2.dist-info/LICENSE
whaller_client-0.1.2.dist-info/METADATA
whaller_client-0.1.2.dist-info/WHEEL
whaller_client-0.1.2.dist-info/top_level.txt
whaller_client-0.1.2.dist-info/RECORD
