Metadata-Version: 2.2
Name: whaller-client
Version: 0.1.2
Summary: Python SDK for interacting with the Whaller API
Home-page: https://github.com/whallerfr/client-python
Author: Whaller
Author-email: Thomas Fauré <thomas.faure@whaller.com>, Alexandre Pinsard <alexandre.pinsard@whaller.fr>
License: MIT
Project-URL: Homepage, https://github.com/whallerfr/client-python
Project-URL: Repository, https://github.com/whallerfr/client-python
Project-URL: Issues, https://github.com/whallerfr/client-python/issues
Requires-Python: >=3.10
License-File: LICENSE
Requires-Dist: requests
Dynamic: author
Dynamic: home-page
Dynamic: requires-python
